fawltydeps/__init__.py
fawltydeps/__main__.py
fawltydeps/check.py
fawltydeps/cli_parser.py
fawltydeps/dir_traversal.py
fawltydeps/extract_deps/__init__.py
fawltydeps/extract_deps/environment_yml_parser.py
fawltydeps/extract_deps/pixi_toml_parser.py
fawltydeps/extract_deps/pyproject_toml_parser.py
fawltydeps/extract_deps/requirements_parser.py
fawltydeps/extract_deps/setup_cfg_parser.py
fawltydeps/extract_deps/setup_py_parser.py
fawltydeps/extract_imports.py
fawltydeps/gitignore_parser.py
fawltydeps/limited_eval.py
fawltydeps/main.py
fawltydeps/packages.py
fawltydeps/settings.py
fawltydeps/traverse_project.py
fawltydeps/types.py
fawltydeps/utils.py
fawltydeps-0.20.0.dist-info/LICENSE
fawltydeps-0.20.0.dist-info/METADATA
fawltydeps-0.20.0.dist-info/WHEEL
fawltydeps-0.20.0.dist-info/entry_points.txt
fawltydeps-0.20.0.dist-info/RECORD
