Metadata-Version: 2.3
Name: fawltydeps
Version: 0.20.0
Summary: Find undeclared and unused 3rd-party dependencies in your Python project.
License: MIT License
Keywords: dependencies,linters,packaging
Author: Nour El Mawass
Author-email: nour.elmawass@tweag.io
Maintainer: Johan Herland
Maintainer-email: johan.herland@tweag.io
Requires-Python: >=3.9.2
Classifier: Development Status :: 4 - Beta
Classifier: Topic :: Software Development :: Libraries :: Python Modules
Classifier: Topic :: Software Development :: Quality Assurance
Classifier: Intended Audience :: Developers
Classifier: Programming Language :: Python
Classifier: Programming Language :: Python :: 3.9
Classifier: Programming Language :: Python :: 3.10
Classifier: Programming Language :: Python :: 3.11
Classifier: Programming Language :: Python :: 3.12
Classifier: Programming Language :: Python :: 3.13
Classifier: Topic :: Utilities
Classifier: Typing :: Typed
Provides-Extra: uv
Requires-Dist: PyYAML (>=6.0.1)
Requires-Dist: importlib_metadata (>=6.6.0)
Requires-Dist: isort (>=5.10)
Requires-Dist: packaging (>=24.0)
Requires-Dist: pip-requirements-parser (>=32.0.1)
Requires-Dist: pydantic (>=1.10.4,<3.0.0)
Requires-Dist: tomli (>=2.0.1) ; python_version < "3.11"
Requires-Dist: uv (>=0.1.6) ; extra == "uv"
Project-URL: Documentation, https://tweag.github.io/FawltyDeps/
Project-URL: Repository, https://github.com/tweag/FawltyDeps
